nestipy_alchemy/__init__.py
nestipy_alchemy/builder.py
nestipy_alchemy/converter/__init__.py
nestipy_alchemy/converter/loader.py
nestipy_alchemy/converter/mapper.py
nestipy_alchemy/converter/mixim.py
nestipy_alchemy/example.py
nestipy_alchemy/module.py
nestipy_alchemy/service.py
nestipy_alchemy-0.2.0.dist-info/LICENSE
nestipy_alchemy-0.2.0.dist-info/METADATA
nestipy_alchemy-0.2.0.dist-info/WHEEL
nestipy_alchemy-0.2.0.dist-info/RECORD
