Metadata-Version: 2.1
Name: nestipy-alchemy
Version: 0.2.0
Summary: Sqlalchemy module for nestipy framework.
Author: tsiresymila
Author-email: tsiresymila@gmail.com
Requires-Python: >=3.11,<4.0
Classifier: Programming Language :: Python :: 3
Classifier: Programming Language :: Python :: 3.11
Classifier: Programming Language :: Python :: 3.12
Requires-Dist: sqlalchemy[asyncio] (>=2.0.31,<3.0.0)
